MANIFEST.in
setup.py
mcider/__init__.py
mcider/cli_helper.py
mcider/converter.py
mcider/main.py
mcider/util.py
mcider.egg-info/PKG-INFO
mcider.egg-info/SOURCES.txt
mcider.egg-info/dependency_links.txt
mcider.egg-info/entry_points.txt
mcider.egg-info/requires.txt
mcider.egg-info/top_level.txt
mcider/themes/io2011/base.html
mcider/themes/io2011/css/styles.css
mcider/themes/io2011/images/colorbar.png
mcider/themes/io2011/images/google-logo-small.png
mcider/themes/io2011/images/google-logo.png
mcider/themes/io2011/images/googleio-logo.png
mcider/themes/io2011/js/prettify.js
mcider/themes/io2011/js/slide-resize.js
mcider/themes/io2011/js/slides.js
mcider/themes/io2012/base.html
mcider/themes/io2012/css/default.css
mcider/themes/io2012/css/phone.css
mcider/themes/io2012/images/google_developers_icon_128.png
mcider/themes/io2012/images/google_developers_logo.png
mcider/themes/io2012/images/google_developers_logo_tiny.png
mcider/themes/io2012/images/google_developers_logo_white.png
mcider/themes/io2012/images/io2012_logo.png
mcider/themes/io2012/js/hammer.js
mcider/themes/io2012/js/modernizr.custom.45394.js
mcider/themes/io2012/js/order.js
mcider/themes/io2012/js/require-1.0.8.min.js
mcider/themes/io2012/js/slide-controller.js
mcider/themes/io2012/js/slide-deck.js
mcider/themes/io2012/js/slide-resize.js
mcider/themes/io2012/js/slide_config.js
mcider/themes/io2012/js/slides.js
mcider/themes/io2012/js/polyfills/classList.min.js
mcider/themes/io2012/js/polyfills/dataset.min.js
mcider/themes/io2012/js/polyfills/history.min.js
mcider/themes/io2012/js/prettify/lang-apollo.js
mcider/themes/io2012/js/prettify/lang-clj.js
mcider/themes/io2012/js/prettify/lang-css.js
mcider/themes/io2012/js/prettify/lang-go.js
mcider/themes/io2012/js/prettify/lang-hs.js
mcider/themes/io2012/js/prettify/lang-lisp.js
mcider/themes/io2012/js/prettify/lang-lua.js
mcider/themes/io2012/js/prettify/lang-ml.js
mcider/themes/io2012/js/prettify/lang-n.js
mcider/themes/io2012/js/prettify/lang-proto.js
mcider/themes/io2012/js/prettify/lang-scala.js
mcider/themes/io2012/js/prettify/lang-sql.js
mcider/themes/io2012/js/prettify/lang-tex.js
mcider/themes/io2012/js/prettify/lang-vb.js
