Metadata-Version: 1.1
Name: mcider
Version: 0.2.1
Summary: markdown converter for slideshow
Home-page: http://ogom.github.com/python-mcider
Author: ogom
Author-email: ogom@hotmail.co.jp
License: MIT
Download-URL: https://github.com/ogom/python-mcider
Platform: UNKNOWN
